{
  "openapi": "3.1.1",
  "info": {
    "title": "GestorClientes.API | v1",
    "version": "1.0.0"
  },
  "servers": [
    {
      "url": "https://localhost:7057"
    },
    {
      "url": "http://localhost:5153"
    }
  ],
  "paths": {
    "/clientes-api/Clientes/listar": {
      "get": {
        "tags": [
          "Clientes"
        ],
        "responses": {
          "200": {
            "description": "OK"
          }
        }
      }
    },
    "/clientes-api/Clientes/buscar": {
      "get": {
        "tags": [
          "Clientes"
        ],
        "parameters": [
          {
            "name": "busqueda",
            "in": "query",
            "schema": {
              "type": "string"
            }
          }
        ],
        "responses": {
          "200": {
            "description": "OK"
          }
        }
      }
    },
    "/clientes-api/Clientes/crear": {
      "post": {
        "tags": [
          "Clientes"
        ],
        "requestBody": {
          "content": {
            "application/json": {
              "schema": {
                "$ref": "#/components/schemas/ClienteDTO"
              }
            },
            "text/json": {
              "schema": {
                "$ref": "#/components/schemas/ClienteDTO"
              }
            },
            "application/*+json": {
              "schema": {
                "$ref": "#/components/schemas/ClienteDTO"
              }
            }
          },
          "required": true
        },
        "responses": {
          "200": {
            "description": "OK"
          }
        }
      }
    },
    "/clientes-api/Clientes/{id}/editar": {
      "put": {
        "tags": [
          "Clientes"
        ],
        "parameters": [
          {
            "name": "id",
            "in": "path",
            "required": true,
            "schema": {
              "pattern": "^-?(?:0|[1-9]\\d*)$",
              "type": "integer",
              "format": "int32"
            }
          }
        ],
        "requestBody": {
          "content": {
            "application/json": {
              "schema": {
                "$ref": "#/components/schemas/ClienteDTO"
              }
            },
            "text/json": {
              "schema": {
                "$ref": "#/components/schemas/ClienteDTO"
              }
            },
            "application/*+json": {
              "schema": {
                "$ref": "#/components/schemas/ClienteDTO"
              }
            }
          },
          "required": true
        },
        "responses": {
          "200": {
            "description": "OK"
          }
        }
      }
    },
    "/clientes-api/Clientes/{id}/eliminar": {
      "delete": {
        "tags": [
          "Clientes"
        ],
        "parameters": [
          {
            "name": "id",
            "in": "path",
            "required": true,
            "schema": {
              "pattern": "^-?(?:0|[1-9]\\d*)$",
              "type": "integer",
              "format": "int32"
            }
          }
        ],
        "responses": {
          "200": {
            "description": "OK"
          }
        }
      }
    }
  },
  "components": {
    "schemas": {
      "ClienteDTO": {
        "required": [
          "nombre",
          "email"
        ],
        "type": "object",
        "properties": {
          "nombre": {
            "type": "string"
          },
          "email": {
            "type": "string"
          }
        }
      }
    }
  },
  "tags": [
    {
      "name": "Clientes"
    }
  ]
}